<?xml version="1.0" encoding="utf-8"?>
<NinjaTrader>
  <Rectangle xmlns:xsd="http://www.w3.org/2001/XMLSchema" xmlns:xsi="http://www.w3.org/2001/XMLSchema-instance">
    <IsAutoScale>false</IsAutoScale>
    <MaxValue>-1.7976931348623157E+308</MaxValue>
    <MinValue>1.7976931348623157E+308</MinValue>
    <DisplayOnChartsMenus>true</DisplayOnChartsMenus>
    <GlobalLastSeenSerialize>0</GlobalLastSeenSerialize>
    <GlobalWorkspace>Spreads</GlobalWorkspace>
    <IsLocked>true</IsLocked>
    <PanelIndex>0</PanelIndex>
    <ZOrderType>Normal</ZOrderType>
    <AreaBrushSerialize>&lt;SolidColorBrush xmlns="http://schemas.microsoft.com/winfx/2006/xaml/presentation"&gt;#FF6495ED&lt;/SolidColorBrush&gt;</AreaBrushSerialize>
    <AreaOpacity>20</AreaOpacity>
    <OutlineStroke>
      <IsOpacityVisible>true</IsOpacityVisible>
      <BrushSerialize>&lt;SolidColorBrush Color="#FF6495ED" Opacity="0" xmlns="http://schemas.microsoft.com/winfx/2006/xaml/presentation" /&gt;</BrushSerialize>
      <DashStyleHelper>Solid</DashStyleHelper>
      <Opacity>0</Opacity>
      <Width>2</Width>
    </OutlineStroke>
    <EndAnchor>
      <SlotIndex>13993</SlotIndex>
      <DisplayName>End</DisplayName>
      <IsBrowsable>true</IsBrowsable>
      <Time>2022-12-21T17:00:00</Time>
      <Price>0.66815</Price>
    </EndAnchor>
    <MiddleAnchor>
      <SlotIndex>25062</SlotIndex>
      <DisplayName>Middle</DisplayName>
      <IsBrowsable>false</IsBrowsable>
      <Time>2021-06-08T12:24:00</Time>
      <Price>27.628414587240144</Price>
    </MiddleAnchor>
    <StartAnchor>
      <SlotIndex>5016</SlotIndex>
      <DisplayName>Start</DisplayName>
      <IsBrowsable>true</IsBrowsable>
      <Time>2022-12-15T09:01:00</Time>
      <Price>0.66865000000000008</Price>
    </StartAnchor>
    <FullTypeName>NinjaTrader.NinjaScript.DrawingTools.Rectangle</FullTypeName>
    <IsGlobalDrawingObjectDefault>true</IsGlobalDrawingObjectDefault>
    <IsOwnerVisible>true</IsOwnerVisible>
  </Rectangle>
</NinjaTrader>